NewYear/__init__.py
NewYear-0.0.2.dist-info/METADATA
NewYear-0.0.2.dist-info/WHEEL
NewYear-0.0.2.dist-info/license .txt
NewYear-0.0.2.dist-info/top_level.txt
NewYear-0.0.2.dist-info/RECORD
