Metadata-Version: 2.1
Name: NewYear
Version: 0.0.2
Summary: Happy new year all of you
Home-page: UNKNOWN
Author: Mr.Alone
License: UNKNOWN
Platform: UNKNOWN
Classifier: Programming Language :: Python :: 3
Classifier: License :: OSI Approved :: MIT License
Classifier: Operating System :: OS Independent
